fondat/annotation.py
fondat/asgi.py
fondat/codec.py
fondat/context.py
fondat/csv.py
fondat/data.py
fondat/error.py
fondat/file.py
fondat/http.py
fondat/lazy.py
fondat/memory.py
fondat/monitoring.py
fondat/openapi.py
fondat/pagination.py
fondat/patch.py
fondat/resource.py
fondat/security.py
fondat/sql.py
fondat/sqlite.py
fondat/stream.py
fondat/string.py
fondat/types.py
fondat/validation.py
fondat_core-3.0.18.dist-info/LICENSE
fondat_core-3.0.18.dist-info/WHEEL
fondat_core-3.0.18.dist-info/METADATA
fondat_core-3.0.18.dist-info/RECORD
