Metadata-Version: 2.1
Name: fondat-core
Version: 3.0.18
Summary: A foundation for asynchronous Python resource-oriented applications.
Home-page: https://github.com/fondat/fondat/
License: MIT
Keywords: asgi,framework,resource,openapi
Author: fondat-core authors
Requires-Python: >=3.9,<4.0
Classifier: Development Status :: 5 - Production/Stable
Classifier: Intended Audience :: Developers
Classifier: License :: OSI Approved :: MIT License
Classifier: Programming Language :: Python :: 3
Classifier: Programming Language :: Python :: 3.10
Classifier: Programming Language :: Python :: 3.9
Classifier: Topic :: Software Development :: Libraries :: Application Frameworks
Requires-Dist: aiosqlite (>=0.16,<0.17)
Requires-Dist: iso8601 (>=0.1,<0.2)
Requires-Dist: multidict (>=5.2,<6.0)
Requires-Dist: wrapt (>=1.13,<2.0)
Project-URL: Documentation, https://github.com/fondat/fondat/tree/main/docs
